MANIFEST.in
requirements.txt
setup.py
mozpay/__init__.py
mozpay/exc.py
mozpay/processor.py
mozpay/verify.py
mozpay.egg-info/PKG-INFO
mozpay.egg-info/SOURCES.txt
mozpay.egg-info/dependency_links.txt
mozpay.egg-info/requires.txt
mozpay.egg-info/top_level.txt
mozpay/djangoapp/__init__.py
mozpay/djangoapp/models.py
mozpay/djangoapp/signals.py
mozpay/djangoapp/urls.py
mozpay/djangoapp/views.py