Metadata-Version: 1.0
Name: mozpay
Version: 2.1.0
Summary: Make web payments with Mozilla's navigator.mozPay().
Home-page: https://github.com/mozilla/mozpay-py
Author: Kumar McMillan
Author-email: kumar.mcmillan@gmail.com
License: MPL 2.0 (Mozilla Public License)
Platform: UNKNOWN
